bloombee/__init__.py
bloombee/constants.py
bloombee/data_structures.py
bloombee/dht_utils.py
bloombee/cli/__init__.py
bloombee/cli/run_dht.py
bloombee/cli/run_server.py
bloombee/client/__init__.py
bloombee/client/config.py
bloombee/client/from_pretrained.py
bloombee/client/inference_session.py
bloombee/client/lm_head.py
bloombee/client/ptune.py
bloombee/client/remote_forward_backward.py
bloombee/client/remote_generation.py
bloombee/client/remote_sequential.py
bloombee/client/sequential_autograd.py
bloombee/client/routing/__init__.py
bloombee/client/routing/sequence_info.py
bloombee/client/routing/sequence_manager.py
bloombee/client/routing/spending_policy.py
bloombee/models/__init__.py
bloombee/models/bloom/__init__.py
bloombee/models/bloom/block.py
bloombee/models/bloom/config.py
bloombee/models/bloom/model.py
bloombee/models/falcon/__init__.py
bloombee/models/falcon/block.py
bloombee/models/falcon/config.py
bloombee/models/falcon/model.py
bloombee/models/llama/__init__.py
bloombee/models/llama/block.py
bloombee/models/llama/config.py
bloombee/models/llama/model.py
bloombee/models/llama/speculative_model.py
bloombee/models/mixtral/__init__.py
bloombee/models/mixtral/block.py
bloombee/models/mixtral/config.py
bloombee/models/mixtral/model.py
bloombee/server/__init__.py
bloombee/server/backend.py
bloombee/server/block_functions.py
bloombee/server/block_selection.py
bloombee/server/block_utils.py
bloombee/server/from_pretrained.py
bloombee/server/handler.py
bloombee/server/memory_cache.py
bloombee/server/reachability.py
bloombee/server/server.py
bloombee/server/task_pool.py
bloombee/server/task_prioritizer.py
bloombee/server/throughput.py
bloombee/utils/__init__.py
bloombee/utils/asyncio.py
bloombee/utils/auto_config.py
bloombee/utils/convert_block.py
bloombee/utils/cuda_graphs.py
bloombee/utils/dht.py
bloombee/utils/disk_cache.py
bloombee/utils/hf_auth.py
bloombee/utils/logging.py
bloombee/utils/misc.py
bloombee/utils/packaging.py
bloombee/utils/peft.py
bloombee-0.1.3.dist-info/LICENSE
bloombee-0.1.3.dist-info/METADATA
bloombee-0.1.3.dist-info/WHEEL
bloombee-0.1.3.dist-info/top_level.txt
bloombee-0.1.3.dist-info/RECORD
