Metadata-Version: 2.1
Name: bloombee
Version: 0.1.3
Summary: A short description of your project
Home-page: https://github.com/yottalabsai/bloombee
Author: Sophie
Author-email: syang127@ucmerced.edu
License: UNKNOWN
Project-URL: Bug Tracker, https://github.com/yottalabsai/bloombee/issues
Platform: UNKNOWN
Classifier: Development Status :: 4 - Beta
Classifier: Intended Audience :: Developers
Classifier: Intended Audience :: Science/Research
Classifier: License :: OSI Approved :: Apache Software License
Classifier: Programming Language :: Python :: 3
Classifier: Programming Language :: Python :: 3.8
Classifier: Programming Language :: Python :: 3.9
Classifier: Programming Language :: Python :: 3.10
Classifier: Programming Language :: Python :: 3.11
Classifier: Topic :: Scientific/Engineering
Classifier: Topic :: Scientific/Engineering :: Mathematics
Classifier: Topic :: Scientific/Engineering :: Artificial Intelligence
Classifier: Topic :: Software Development
Classifier: Topic :: Software Development :: Libraries
Classifier: Topic :: Software Development :: Libraries :: Python Modules
Requires-Python: >=3.8
Requires-Dist: torch >=1.12
Requires-Dist: bitsandbytes ==0.41.1
Requires-Dist: accelerate >=0.27.2
Requires-Dist: huggingface-hub <1.0.0,>=0.11.1
Requires-Dist: tokenizers >=0.13.3
Requires-Dist: transformers ==4.43.1
Requires-Dist: speedtest-cli ==2.1.3
Requires-Dist: hivemind
Requires-Dist: tensor-parallel ==1.0.23
Requires-Dist: humanfriendly
Requires-Dist: async-timeout >=4.0.2
Requires-Dist: packaging >=20.9
Requires-Dist: sentencepiece >=0.1.99
Requires-Dist: peft ==0.8.2
Requires-Dist: safetensors >=0.3.1
Requires-Dist: Dijkstar >=2.6.0
Requires-Dist: numpy <2
Requires-Dist: cpufeature >=0.2.0 ; platform_machine == "x86_64"
Provides-Extra: dev
Requires-Dist: pytest ==6.2.5 ; extra == 'dev'
Requires-Dist: pytest-forked ; extra == 'dev'
Requires-Dist: pytest-asyncio ==0.16.0 ; extra == 'dev'
Requires-Dist: black ==22.3.0 ; extra == 'dev'
Requires-Dist: isort ==5.10.1 ; extra == 'dev'
Requires-Dist: psutil ; extra == 'dev'
